openkongqi/__init__.py
openkongqi/apikeys.py
openkongqi/bin.py
openkongqi/conf.py
openkongqi/exceptions.py
openkongqi/fetch.py
openkongqi/filecache.py
openkongqi/routes.py
openkongqi/sched.py
openkongqi/stations.py
openkongqi/tasks.py
openkongqi/utils.py
openkongqi/cache/__init__.py
openkongqi/cache/base.py
openkongqi/cache/redisdb.py
openkongqi/data/user_agent_strings.json
openkongqi/data/sources/pm25.in.json
openkongqi/data/stations/cn/shanghai.json
openkongqi/records/__init__.py
openkongqi/records/base.py
openkongqi/records/mysql.py
openkongqi/records/pgsql.py
openkongqi/records/sqlalch.py
openkongqi/records/sqlite3.py
openkongqi/source/__init__.py
openkongqi/source/base.py
openkongqi/source/pm25in.py
openkongqi/status/__init__.py
openkongqi/status/base.py
openkongqi/status/redisdb.py
utils/__init__.py
utils/get_user_agent_strings.py
utils/source_test.py
openkongqi-0.2.13.dist-info/LICENSE
openkongqi-0.2.13.dist-info/METADATA
openkongqi-0.2.13.dist-info/WHEEL
openkongqi-0.2.13.dist-info/entry_points.txt
openkongqi-0.2.13.dist-info/top_level.txt
openkongqi-0.2.13.dist-info/RECORD
