Metadata-Version: 2.1
Name: openkongqi
Version: 0.2.13
Summary: Outdoor air quality data
Home-page: https://github.com/gams/openkongqi
Author: Stefan Berder
Author-email: stefan@measureofqualty.com
License: Apache License 2.0
Keywords: air quality
Platform: UNKNOWN
Classifier: Development Status :: 1 - Planning
Classifier: Environment :: Console
Classifier: Framework :: Sphinx
Classifier: Intended Audience :: Developers
Classifier: Intended Audience :: Healthcare Industry
Classifier: Intended Audience :: Science/Research
Classifier: Natural Language :: Chinese (Simplified)
Classifier: Natural Language :: English
Classifier: Operating System :: OS Independent
Classifier: Programming Language :: Python :: 2.7
Classifier: Topic :: Text Processing :: Markup :: HTML
Classifier: Topic :: Text Processing :: Markup :: XML
Requires-Dist: beautifulsoup4 ==4.9.3
Requires-Dist: celery ==4.4.7
Requires-Dist: hiredis ==2.3.2
Requires-Dist: html5lib ==1.1
Requires-Dist: pytz >=2024.1
Requires-Dist: redis ==5.0.4
Requires-Dist: requests >=2.31.0
Requires-Dist: six >=1.13.0
Requires-Dist: sqlalchemy >=1.4.1
